{
  "name": "deferred",
  "swapchain": {
    "format": "B8G8R8A8_UNORM",
    "images": 2
  },
  "depthbuffer": {
    "width": 1.0,
    "height": 1.0,
    "format": "D32_SFLOAT"
  },
  "framebuffers": [
    {
      "width": 0.5,
      "height": 0.5,
      "format": "R16G16B16A16_UNORM",
      "samples": 4,
      "layer": 1
    },
    {
      "swapchain": true
    }
  ],
  "render_passes": [
    {
      "attachments": [
        {
          "index": 0,
          "loadOp": "",
          "storeOp": "store",
          "stencilLoadOp": "",
          "stencilStoreOp": "",
          "initialLayout": "",
          "finalLayout": "shader_read_only_optimal"
        }
      ],
      "subpasses": [
        {
          "bind_point": "graphics",
          "attachments": [
            {
              "index": 0,
              "layout": "color_attachment_optimal"
            }
          ]
        }
      ]
    }
  ],
  "viewport_state": {
    "viewports": [
      {
        "x": 0.0,
        "y": 0.0,
        "width": 1.0,
        "height": 1.0,
        "minDepth": 0.0,
        "maxDepth": 1.0
      }
    ],
    "scissors": [
      {
        "xOffset": 0,
        "yOffset": 0,
        "width": 1.0,
        "height": 1.0
      }
    ]
  },
  "rasterization_state": {
    "depthClampEnable": false,
    "rasterizerDiscardEnable": false,
    "polygonMode": "fill",
    "cullMode": "back",
    "frontFace": "counter_clockwise",
    "depthBiasEnable": false,
    "depthBiasConstantFactor": 0.0,
    "depthBiasClamp": 0.0,
    "depthBiasSlopeFactor": 0.0,
    "lineWidth": 1.0
  },
  "multisample_state": {
    "rasterizationSamples": 1,
    "sampleShadingEnable": false,
    "minSampleShading": 1.0,
    "alphaToCoverageEnable": false,
    "alphaToOneEnable": false
  },
  "color_blend_state": {
    "logicOpEnable": false,
    "logicOp": "copy",
    "blendConstants": [
      0.0,
      0.0,
      0.0,
      0.0
    ],
    "color_blend_attachment_states": [
      {
        "blendEnable": false,
        "srcColorBlendFactor": "one",
        "dstColorBlendFactor": "zero",
        "colorBlendOp": "add",
        "srcAlphaBlendFactor": "one",
        "dstAlphaBlendFactor": "zero",
        "alphaBlendOp": "add",
        "colorWriteMask": "rgba"
      }
    ]
  }
}